perceiver_pytorch/__init__.py
perceiver_pytorch/experimental.py
perceiver_pytorch/gated.py
perceiver_pytorch/mixed_latents.py
perceiver_pytorch/perceiver_io.py
perceiver_pytorch/perceiver_pytorch.py
perceiver_pytorch-0.8.8.dist-info/LICENSE
perceiver_pytorch-0.8.8.dist-info/METADATA
perceiver_pytorch-0.8.8.dist-info/WHEEL
perceiver_pytorch-0.8.8.dist-info/top_level.txt
perceiver_pytorch-0.8.8.dist-info/RECORD
