Metadata-Version: 2.1
Name: perceiver-pytorch
Version: 0.8.8
Summary: Perceiver - Pytorch
Home-page: https://github.com/lucidrains/perceiver-pytorch
Author: Phil Wang
Author-email: lucidrains@gmail.com
License: MIT
Keywords: artificial intelligence,deep learning,transformer,attention mechanism
Classifier: Development Status :: 4 - Beta
Classifier: Intended Audience :: Developers
Classifier: Topic :: Scientific/Engineering :: Artificial Intelligence
Classifier: License :: OSI Approved :: MIT License
Classifier: Programming Language :: Python :: 3.6
License-File: LICENSE
Requires-Dist: einops >=0.3
Requires-Dist: torch >=1.6
